envoy/gpg/identity/__init__.py
envoy/gpg/identity/identity.py
envoy/gpg/identity/py.typed
envoy.gpg.identity-0.1.1.dist-info/METADATA
envoy.gpg.identity-0.1.1.dist-info/WHEEL
envoy.gpg.identity-0.1.1.dist-info/namespace_packages.txt
envoy.gpg.identity-0.1.1.dist-info/top_level.txt
envoy.gpg.identity-0.1.1.dist-info/RECORD
