Metadata-Version: 2.1
Name: envoy.gpg.identity
Version: 0.1.1
Summary: "GPG identity util used in Envoy proxy's CI"
Home-page: https://github.com/envoyproxy/pytooling/tree/main/envoy.gpg.identity
Author: Ryan Northey
Author-email: ryan@synca.io
Maintainer: Ryan Northey
Maintainer-email: ryan@synca.io
License: Apache Software License 2.0
Requires-Python: >=3.10.0
Requires-Dist: aio.core (>=0.10.0)
Requires-Dist: python-gnupg
